grove/__about__.py
grove/__init__.py
grove/constants.py
grove/exceptions.py
grove/logging.py
grove/models.py
grove/types.py
grove/caches/__init__.py
grove/caches/aws_dynamodb.py
grove/caches/local_file.py
grove/caches/local_memory.py
grove/configs/__init__.py
grove/configs/aws_ssm.py
grove/configs/local_file.py
grove/connectors/__init__.py
grove/connectors/atlassian/__init__.py
grove/connectors/atlassian/api.py
grove/connectors/atlassian/audit_events.py
grove/connectors/dropbox/__init__.py
grove/connectors/dropbox/api.py
grove/connectors/dropbox/team_events.py
grove/connectors/fleetdm/__init__.py
grove/connectors/fleetdm/api.py
grove/connectors/fleetdm/host_logs.py
grove/connectors/github/__init__.py
grove/connectors/github/api.py
grove/connectors/github/audit_log.py
grove/connectors/gsuite/__init__.py
grove/connectors/gsuite/activities.py
grove/connectors/gsuite/alerts.py
grove/connectors/local/__init__.py
grove/connectors/local/heartbeat.py
grove/connectors/okta/__init__.py
grove/connectors/okta/api.py
grove/connectors/okta/system_log.py
grove/connectors/onepassword/__init__.py
grove/connectors/onepassword/api.py
grove/connectors/onepassword/events_audit.py
grove/connectors/onepassword/events_itemusages.py
grove/connectors/onepassword/events_signinattempts.py
grove/connectors/onepassword/util.py
grove/connectors/oomnitza/__init__.py
grove/connectors/oomnitza/activities.py
grove/connectors/oomnitza/api.py
grove/connectors/pagerduty/__init__.py
grove/connectors/pagerduty/api.py
grove/connectors/pagerduty/audit_records.py
grove/connectors/sf/__init__.py
grove/connectors/sf/event_log.py
grove/connectors/sfmc/__init__.py
grove/connectors/sfmc/api.py
grove/connectors/sfmc/audit_events.py
grove/connectors/sfmc/security_events.py
grove/connectors/slack/__init__.py
grove/connectors/slack/api.py
grove/connectors/slack/audit_logs.py
grove/connectors/snowflake/__init__.py
grove/connectors/snowflake/common.py
grove/connectors/snowflake/login_history.py
grove-2.2.0.dist-info/licenses/LICENSE
grove-2.2.0.dist-info/METADATA
grove-2.2.0.dist-info/WHEEL
grove-2.2.0.dist-info/entry_points.txt
grove-2.2.0.dist-info/top_level.txt
grove-2.2.0.dist-info/RECORD
