Metadata-Version: 2.4
Name: grove
Version: 2.2.0
Summary: A Software as a Service (SaaS) log collection framework.
Author: HashiCorp Security (TDR)
License: MPL-2.0
Classifier: Programming Language :: Python :: 3.9
Classifier: Natural Language :: English
Requires-Python: >=3.9
License-File: LICENSE
Requires-Dist: urllib3<2.0
Requires-Dist: aws-lambda-powertools<3.0,>=2.0
Requires-Dist: boto3<2.0,>=1.26
Requires-Dist: requests<3.0,>=2.28
Requires-Dist: google-api-python-client<3.0,>=2.68
Requires-Dist: simple-salesforce<2.0,>=1.12
Requires-Dist: snowflake-connector-python<4.0,>=3.12.2
Requires-Dist: twilio<8.0,>=7.15
Requires-Dist: pydantic<2.0,>=1.10
Requires-Dist: jmespath<2.0,>=1.0.0
Requires-Dist: stripe<9.0,>=8.4.0
Provides-Extra: tests
Requires-Dist: black; extra == "tests"
Requires-Dist: coverage; extra == "tests"
Requires-Dist: ruff; extra == "tests"
Requires-Dist: types-setuptools; extra == "tests"
Requires-Dist: isort; extra == "tests"
Requires-Dist: mypy; extra == "tests"
Requires-Dist: pip-tools; extra == "tests"
Requires-Dist: mock; extra == "tests"
Requires-Dist: pytest; extra == "tests"
Requires-Dist: pytest-cov; extra == "tests"
Requires-Dist: responses; extra == "tests"
Requires-Dist: tox; extra == "tests"
Requires-Dist: sphinx; extra == "tests"
Requires-Dist: furo; extra == "tests"
Requires-Dist: moto[s3,ssm]<5.0,>=4.0; extra == "tests"
Requires-Dist: types-requests; extra == "tests"
Dynamic: license-file
